jccc/__init__.py
jccc/_numba.py
jccc/_numba.pyi
jccc/convert.py
jccc/convert.pyi
jccc/data/palettes/css4.csv
jccc/data/palettes/css4.npz
jccc/diff.py
jccc/palette.py
jccc/py.typed
jccc/utils.py
jccc-0.1.2.dist-info/LICENSE
jccc-0.1.2.dist-info/METADATA
jccc-0.1.2.dist-info/WHEEL
jccc-0.1.2.dist-info/RECORD
